[
  {
    "id": "akbar_1574_mansabdari_system",
    "era": "Mughal Empire",
    "ruler": "Akbar",
    "phase": "Administrative & Cultural Golden Age",
    "year": 1574,
    "event": "Introduction of the Mansabdari System",
    "situation": "Akbar needed an efficient system to manage nobles, military officers, and civil administrators across a growing empire.",
    "facts": [
      "The Mansabdari system ranked officials by numerical grades.",
      "Ranks determined military command and salary.",
      "The system reduced hereditary power of nobles."
    ],
    "choices": [
      "Implement the Mansabdari system to centralize administration.",
      "Continue with traditional feudal and hereditary appointments."
    ],
    "recommended_condition": "balanced",
    "learning_focus": "Understanding bureaucratic reforms and centralized governance.",
    "source": "Akbarnama and Mughal administrative reforms, 1574"
  }
  ,
  {
    "id": "akbar_1575_ibadat_khana",
    "era": "Mughal Empire",
    "ruler": "Akbar",
    "phase": "Administrative & Cultural Golden Age",
    "year": 1575,
    "event": "Construction of the Ibadat Khana for interfaith debate",
    "situation": "Akbar sought to promote religious dialogue and understanding within his diverse empire.",
    "facts": [
      "Ibadat Khana was located in Fatehpur Sikri.",
      "Scholars of Islam, Hinduism, Jainism, Christianity, and other faiths were invited.",
      "The debates influenced Akbar’s policies of religious tolerance."
    ],
    "choices": [
      "Encourage open interfaith discussions at Ibadat Khana.",
      "Limit religious debate to Islamic scholars only."
    ],
    "recommended_condition": "balanced",
    "learning_focus": "Exploring the role of intellectual dialogue in shaping inclusive governance.",
    "source": "Akbarnama and Mughal court records, 1575"
  }
  ,
  {
    "id": "akbar_1575_tukaroi_battle",
    "era": "Mughal Empire",
    "ruler": "Akbar",
    "phase": "Administrative & Cultural Golden Age",
    "year": 1575,
    "event": "Victory at the Battle of Tukaroi",
    "situation": "Akbar aimed to bring the wealthy and strategically important Bengal region under Mughal control.",
    "facts": [
      "The battle was fought against the Bengal Sultanate.",
      "Victory extended Mughal authority into eastern India.",
      "Bengal was a rich region with major trade and agricultural resources."
    ],
    "choices": [
      "Annex Bengal directly into the Mughal Empire.",
      "Establish a vassal arrangement with local rulers to maintain influence."
    ],
    "recommended_condition": "strong",
    "learning_focus": "Understanding military conquest as a tool for territorial expansion and economic control.",
    "source": "Akbarnama and Mughal military chronicles, 1575"
  }
  ,
  {
    "id": "akbar_1576_haldighati_battle",
    "era": "Mughal Empire",
    "ruler": "Akbar",
    "phase": "Administrative & Cultural Golden Age",
    "year": 1576,
    "event": "Battle of Haldighati against Maharana Pratap",
    "situation": "Akbar sought to assert control over Mewar, a stronghold of Rajput resistance in central India.",
    "facts": [
      "Maharana Pratap led the Rajput forces against the Mughals.",
      "The battle was strategically important for control of Rajasthan's interior.",
      "Mughal forces had superior numbers and artillery."
    ],
    "choices": [
      "Engage in full-scale battle to assert Mughal authority.",
      "Seek a negotiated settlement to integrate Mewar peacefully."
    ],
    "recommended_condition": "strong",
    "learning_focus": "Evaluating military strategy versus diplomacy in consolidating power.",
    "source": "Akbarnama and Mughal military records, 1576"
  }
  ,
  {
    "id": "akbar_1576_bengal_annexation",
    "era": "Mughal Empire",
    "ruler": "Akbar",
    "phase": "Administrative & Cultural Golden Age",
    "year": 1576,
    "event": "Formal annexation of Bengal into the Mughal Empire",
    "situation": "Following military victories, Akbar decided how to govern Bengal, a wealthy and strategically vital region.",
    "facts": [
      "Bengal was a major center of agriculture and textile production.",
      "The region had previously been ruled by the Bengal Sultanate.",
      "Direct control increased imperial revenue and trade influence."
    ],
    "choices": [
      "Annex Bengal as a Mughal province under direct administration.",
      "Allow semi-autonomous rule under local elites loyal to the empire."
    ],
    "recommended_condition": "strong",
    "learning_focus": "Understanding the economic and administrative impact of territorial annexation.",
    "source": "Akbarnama and Mughal administrative records, 1576"
  }
  ,
  {
    "id": "akbar_1579_mazhar_decree",
    "era": "Mughal Empire",
    "ruler": "Akbar",
    "phase": "Administrative & Cultural Golden Age",
    "year": 1579,
    "event": "Issuance of the Mazhar Decree",
    "situation": "Akbar sought to reduce religious factionalism and assert imperial authority over competing religious interpretations.",
    "facts": [
      "The Mazhar declared the emperor as final arbiter in religious disputes.",
      "It limited the influence of orthodox Islamic scholars.",
      "The decree strengthened centralized authority."
    ],
    "choices": [
      "Assert imperial authority over religious matters through the decree.",
      "Maintain clerical independence to avoid religious opposition."
    ],
    "recommended_condition": "unstable",
    "learning_focus": "Analyzing the risks of centralizing religious authority within political power.",
    "source": "Akbarnama and Mughal legal decrees, 1579"
  }
  ,
  {
    "id": "akbar_1580_dahsala_system",
    "era": "Mughal Empire",
    "ruler": "Akbar",
    "phase": "Administrative & Cultural Golden Age",
    "year": 1580,
    "event": "Implementation of the Dahsala land-revenue system",
    "situation": "Akbar sought a fair and predictable revenue system to support a growing empire and reduce agrarian unrest.",
    "facts": [
      "The Dahsala system averaged land revenue over ten years.",
      "It was developed under Raja Todar Mal.",
      "Revenue was assessed based on crop type and land productivity."
    ],
    "choices": [
      "Implement the Dahsala system to standardize land revenue collection.",
      "Continue with variable and locally negotiated revenue assessments."
    ],
    "recommended_condition": "balanced",
    "learning_focus": "Understanding economic reforms and their role in long-term political stability.",
    "source": "Ain-i-Akbari and Mughal revenue administration records, 1580"
  }
  ,
  {
    "id": "akbar_1581_kabul_campaign",
    "era": "Mughal Empire",
    "ruler": "Akbar",
    "phase": "Administrative & Cultural Golden Age",
    "year": 1581,
    "event": "Akbar’s Kabul campaign against his rebellious half-brother",
    "situation": "Akbar faced a dynastic rebellion that threatened imperial unity and control over the northwestern frontier.",
    "facts": [
      "The rebellion was led by Akbar’s half-brother in Kabul.",
      "Akbar personally commanded the campaign.",
      "He became the first Mughal emperor to cross the Indus River in victory."
    ],
    "choices": [
      "Lead the army personally to crush the rebellion decisively.",
      "Delegate the campaign to generals and focus on internal administration."
    ],
    "recommended_condition": "strong",
    "learning_focus": "Examining personal leadership and dynastic control in imperial stability.",
    "source": "Akbarnama and Mughal frontier campaign accounts, 1581"
  }
]
